{
  "counselling": "MH",
  "year": 2025,
  "quota_type": "GOVT_MBBS",
  "category": "ST",
  "sub_type": "GENERAL",
  "colleges": [
    {
      "code": "1103",
      "name": "Seth G.S. Medical College, Mumbai",
      "establishment": 1925,
      "fees": "16,550",
      "rounds": {
        "Round 1": {
          "Intake": 9,
          "AIR": 86876,
          "SML": 7339,
          "CSML": "ST-19"
        },
        "Round 2": {
          "Intake": 4,
          "AIR": 110266,
          "SML": 9327,
          "CSML": "ST-31"
        },
        "Round 3": {
          "Intake": 2,
          "AIR": 146330,
          "SML": 12089,
          "CSML": "ST-44"
        },
        "Stray Round 1": {
          "Intake": 0,
          "AIR": null,
          "SML": null,
          "CSML": null
        },
        "Stray Round 2": {
          "Intake": null,
          "AIR": null,
          "SML": null,
          "CSML": null
        },
        "Stray Round 3": {
          "Intake": null,
          "AIR": null,
          "SML": null,
          "CSML": null
        }
      }
    },
    {
      "code": "1110",
      "name": "B.J. Government Medical College, Pune",
      "establishment": 1964,
      "fees": "14,607",
      "rounds": {
        "Round 1": {
          "Intake": 9,
          "AIR": 122469,
          "SML": 10302,
          "CSML": "ST-36"
        },
        "Round 2": {
          "Intake": 1,
          "AIR": 136719,
          "SML": 11399,
          "CSML": "ST-42"
        },
        "Round 3": {
          "Intake": 0,
          "AIR": null,
          "SML": null,
          "CSML": null
        },
        "Stray Round 1": {
          "Intake": 0,
          "AIR": null,
          "SML": null,
          "CSML": null
        },
        "Stray Round 2": {
          "Intake": null,
          "AIR": null,
          "SML": null,
          "CSML": null
        },
        "Stray Round 3": {
          "Intake": null,
          "AIR": null,
          "SML": null,
          "CSML": null
        }
      }
    },
    {
      "code": "1221",
      "name": "Government Medical College, Nagpur",
      "establishment": 1947,
      "fees": "13,000",
      "rounds": {
        "Round 1": {
          "Intake": 9,
          "AIR": 214699,
          "SML": 16911,
          "CSML": "ST-95"
        },
        "Round 2": {
          "Intake": 0,
          "AIR": 154306,
          "SML": 12710,
          "CSML": "ST-51"
        },
        "Round 3": {
          "Intake": 0,
          "AIR": null,
          "SML": null,
          "CSML": null
        },
        "Stray Round 1": {
          "Intake": 0,
          "AIR": null,
          "SML": null,
          "CSML": null
        },
        "Stray Round 2": {
          "Intake": null,
          "AIR": null,
          "SML": null,
          "CSML": null
        },
        "Stray Round 3": {
          "Intake": null,
          "AIR": null,
          "SML": null,
          "CSML": null
        }
      }
    },
    {
      "code": "1101",
      "name": "Grant Medical College, Mumbai",
      "establishment": 1845,
      "fees": "13,670",
      "rounds": {
        "Round 1": {
          "Intake": 10,
          "AIR": 137898,
          "SML": 11492,
          "CSML": "ST-44"
        },
        "Round 2": {
          "Intake": 1,
          "AIR": 179998,
          "SML": 14533,
          "CSML": "ST-64"
        },
        "Round 3": {
          "Intake": 0,
          "AIR": null,
          "SML": null,
          "CSML": null
        },
        "Stray Round 1": {
          "Intake": 0,
          "AIR": null,
          "SML": null,
          "CSML": null
        },
        "Stray Round 2": {
          "Intake": null,
          "AIR": null,
          "SML": null,
          "CSML": null
        },
        "Stray Round 3": {
          "Intake": null,
          "AIR": null,
          "SML": null,
          "CSML": null
        }
      }
    },
    {
      "code": "1104",
      "name": "Topiwala Nair Medical College, Mumbai",
      "establishment": 1964,
      "fees": "7,900",
      "rounds": {
        "Round 1": {
          "Intake": 4,
          "AIR": 186608,
          "SML": 14997,
          "CSML": "ST-71"
        },
        "Round 2": {
          "Intake": 0,
          "AIR": 194116,
          "SML": 15538,
          "CSML": "ST-75"
        },
        "Round 3": {
          "Intake": 0,
          "AIR": null,
          "SML": null,
          "CSML": null
        },
        "Stray Round 1": {
          "Intake": 0,
          "AIR": null,
          "SML": null,
          "CSML": null
        },
        "Stray Round 2": {
          "Intake": null,
          "AIR": null,
          "SML": null,
          "CSML": null
        },
        "Stray Round 3": {
          "Intake": null,
          "AIR": null,
          "SML": null,
          "CSML": null
        }
      }
    },
    {
      "code": "1102",
      "name": "Lokmanya Tilak Medical College, Mumbai",
      "establishment": 1964,
      "fees": "9,400",
      "rounds": {
        "Round 1": {
          "Intake": 8,
          "AIR": 195259,
          "SML": 15613,
          "CSML": "ST-77"
        },
        "Round 2": {
          "Intake": 2,
          "AIR": 229124,
          "SML": 17842,
          "CSML": "ST-113"
        },
        "Round 3": {
          "Intake": 0,
          "AIR": 240739,
          "SML": 18481,
          "CSML": "ST-129"
        },
        "Stray Round 1": {
          "Intake": 1,
          "AIR": 357222,
          "SML": 25593,
          "CSML": "ST-410"
        },
        "Stray Round 2": {
          "Intake": null,
          "AIR": null,
          "SML": null,
          "CSML": null
        },
        "Stray Round 3": {
          "Intake": null,
          "AIR": null,
          "SML": null,
          "CSML": null
        }
      }
    },
    {
      "code": "1327",
      "name": "Government Medical College, Aurangabad",
      "establishment": 1956,
      "fees": "13,640",
      "rounds": {
        "Round 1": {
          "Intake": 8,
          "AIR": 234190,
          "SML": 18140,
          "CSML": "ST-120"
        },
        "Round 2": {
          "Intake": 1,
          "AIR": 234190,
          "SML": 18140,
          "CSML": "ST-120"
        },
        "Round 3": {
          "Intake": 1,
          "AIR": 239251,
          "SML": 18393,
          "CSML": "ST-127"
        },
        "Stray Round 1": {
          "Intake": 0,
          "AIR": null,
          "SML": null,
          "CSML": null
        },
        "Stray Round 2": {
          "Intake": null,
          "AIR": null,
          "SML": null,
          "CSML": null
        },
        "Stray Round 3": {
          "Intake": null,
          "AIR": null,
          "SML": null,
          "CSML": null
        }
      }
    },
    {
      "code": "1329",
      "name": "Swami Ramanand Tirth Medical College, Ambejogai",
      "establishment": 1974,
      "fees": "19,250",
      "rounds": {
        "Round 1": {
          "Intake": 6,
          "AIR": 290280,
          "SML": 21591,
          "CSML": "ST-221"
        },
        "Round 2": {
          "Intake": 0,
          "AIR": 238211,
          "SML": 18404,
          "CSML": "ST-125"
        },
        "Round 3": {
          "Intake": 1,
          "AIR": 299118,
          "SML": 22041,
          "CSML": "ST-241"
        },
        "Stray Round 1": {
          "Intake": 0,
          "AIR": null,
          "SML": null,
          "CSML": null
        },
        "Stray Round 2": {
          "Intake": null,
          "AIR": null,
          "SML": null,
          "CSML": null
        },
        "Stray Round 3": {
          "Intake": null,
          "AIR": null,
          "SML": null,
          "CSML": null
        }
      }
    },
    {
      "code": "1109",
      "name": "Rajiv Gandhi Medical College, Kalwa, Thane",
      "establishment": 1992,
      "fees": "13,760",
      "rounds": {
        "Round 1": {
          "Intake": 4,
          "AIR": 230180,
          "SML": 17905,
          "CSML": "ST-115"
        },
        "Round 2": {
          "Intake": 1,
          "AIR": 240739,
          "SML": 18571,
          "CSML": "ST-133"
        },
        "Round 3": {
          "Intake": 1,
          "AIR": 265011,
          "SML": 19960,
          "CSML": "ST-161"
        },
        "Stray Round 1": {
          "Intake": 0,
          "AIR": null,
          "SML": null,
          "CSML": null
        },
        "Stray Round 2": {
          "Intake": null,
          "AIR": null,
          "SML": null,
          "CSML": null
        },
        "Stray Round 3": {
          "Intake": null,
          "AIR": null,
          "SML": null,
          "CSML": null
        }
      }
    },
    {
      "code": "1150",
      "name": "Government Medical College, Baramati",
      "establishment": 2019,
      "fees": "14,000",
      "rounds": {
        "Round 1": {
          "Intake": 4,
          "AIR": 242627,
          "SML": 18684,
          "CSML": "ST-136"
        },
        "Round 2": {
          "Intake": 1,
          "AIR": 243373,
          "SML": 18718,
          "CSML": "ST-137"
        },
        "Round 3": {
          "Intake": 1,
          "AIR": 181657,
          "SML": 14581,
          "CSML": "ST-66"
        },
        "Stray Round 1": {
          "Intake": 1,
          "AIR": 360344,
          "SML": 25791,
          "CSML": "ST-427"
        },
        "Stray Round 2": {
          "Intake": null,
          "AIR": null,
          "SML": null,
          "CSML": null
        },
        "Stray Round 3": {
          "Intake": null,
          "AIR": null,
          "SML": null,
          "CSML": null
        }
      }
    },
    {
      "code": "1132",
      "name": "R.C.S.M. Medical College, Kolhapur",
      "establishment": 2001,
      "fees": "14,000",
      "rounds": {
        "Round 1": {
          "Intake": 6,
          "AIR": 265743,
          "SML": 20108,
          "CSML": "ST-167"
        },
        "Round 2": {
          "Intake": 0,
          "AIR": 245326,
          "SML": 18835,
          "CSML": "ST-142"
        },
        "Round 3": {
          "Intake": 0,
          "AIR": null,
          "SML": null,
          "CSML": null
        },
        "Stray Round 1": {
          "Intake": 0,
          "AIR": null,
          "SML": null,
          "CSML": null
        },
        "Stray Round 2": {
          "Intake": null,
          "AIR": null,
          "SML": null,
          "CSML": null
        },
        "Stray Round 3": {
          "Intake": null,
          "AIR": null,
          "SML": null,
          "CSML": null
        }
      }
    },
    {
      "code": "1222",
      "name": "Indira Gandhi Medical College, Nagpur",
      "establishment": 1968,
      "fees": "16,950",
      "rounds": {
        "Round 1": {
          "Intake": 8,
          "AIR": 241948,
          "SML": 18647,
          "CSML": "ST-135"
        },
        "Round 2": {
          "Intake": 3,
          "AIR": 246390,
          "SML": 18904,
          "CSML": "ST-145"
        },
        "Round 3": {
          "Intake": 0,
          "AIR": null,
          "SML": null,
          "CSML": null
        },
        "Stray Round 1": {
          "Intake": 0,
          "AIR": null,
          "SML": null,
          "CSML": null
        },
        "Stray Round 2": {
          "Intake": null,
          "AIR": null,
          "SML": null,
          "CSML": null
        },
        "Stray Round 3": {
          "Intake": null,
          "AIR": null,
          "SML": null,
          "CSML": null
        }
      }
    },
    {
      "code": "1115",
      "name": "Government Medical College, Miraj",
      "establishment": 1962,
      "fees": "12,500",
      "rounds": {
        "Round 1": {
          "Intake": 8,
          "AIR": 266375,
          "SML": 20144,
          "CSML": "ST-168"
        },
        "Round 2": {
          "Intake": 0,
          "AIR": 266770,
          "SML": 20174,
          "CSML": "ST-169"
        },
        "Round 3": {
          "Intake": 0,
          "AIR": 283585,
          "SML": 21071,
          "CSML": "ST-199"
        },
        "Stray Round 1": {
          "Intake": 0,
          "AIR": null,
          "SML": null,
          "CSML": null
        },
        "Stray Round 2": {
          "Intake": null,
          "AIR": null,
          "SML": null,
          "CSML": null
        },
        "Stray Round 3": {
          "Intake": null,
          "AIR": null,
          "SML": null,
          "CSML": null
        }
      }
    },
    {
      "code": "1114",
      "name": "Dr. Vaishampayan Government Medical College, Solapur",
      "establishment": 1963,
      "fees": "13,000",
      "rounds": {
        "Round 1": {
          "Intake": 6,
          "AIR": 256672,
          "SML": 19525,
          "CSML": "ST-152"
        },
        "Round 2": {
          "Intake": 2,
          "AIR": 268488,
          "SML": 20290,
          "CSML": "ST-172"
        },
        "Round 3": {
          "Intake": 1,
          "AIR": 273635,
          "SML": 20517,
          "CSML": "ST-181"
        },
        "Stray Round 1": {
          "Intake": 0,
          "AIR": null,
          "SML": null,
          "CSML": null
        },
        "Stray Round 2": {
          "Intake": null,
          "AIR": null,
          "SML": null,
          "CSML": null
        },
        "Stray Round 3": {
          "Intake": null,
          "AIR": null,
          "SML": null,
          "CSML": null
        }
      }
    },
    {
      "code": "1163",
      "name": "Government Medical College, Mumbai & GT Hospital",
      "establishment": 2024,
      "fees": "13,670",
      "rounds": {
        "Round 1": {
          "Intake": 2,
          "AIR": 246390,
          "SML": 18904,
          "CSML": "ST-145"
        },
        "Round 2": {
          "Intake": 1,
          "AIR": 270670,
          "SML": 20435,
          "CSML": "ST-181"
        },
        "Round 3": {
          "Intake": 1,
          "AIR": 244388,
          "SML": 18698,
          "CSML": "ST-137"
        },
        "Stray Round 1": {
          "Intake": 1,
          "AIR": 370202,
          "SML": 26407,
          "CSML": "ST-462"
        },
        "Stray Round 2": {
          "Intake": null,
          "AIR": null,
          "SML": null,
          "CSML": null
        },
        "Stray Round 3": {
          "Intake": null,
          "AIR": null,
          "SML": null,
          "CSML": null
        }
      }
    },
    {
      "code": "1328",
      "name": "Government Medical College, Nanded",
      "establishment": 1988,
      "fees": "8,500",
      "rounds": {
        "Round 1": {
          "Intake": 6,
          "AIR": 270670,
          "SML": 20435,
          "CSML": "ST-181"
        },
        "Round 2": {
          "Intake": 0,
          "AIR": 278149,
          "SML": 20881,
          "CSML": "ST-193"
        },
        "Round 3": {
          "Intake": 0,
          "AIR": null,
          "SML": null,
          "CSML": null
        },
        "Stray Round 1": {
          "Intake": 0,
          "AIR": null,
          "SML": null,
          "CSML": null
        },
        "Stray Round 2": {
          "Intake": null,
          "AIR": null,
          "SML": null,
          "CSML": null
        },
        "Stray Round 3": {
          "Intake": null,
          "AIR": null,
          "SML": null,
          "CSML": null
        }
      }
    },
    {
      "code": "1234",
      "name": "Government Medical College, Akola",
      "establishment": 2002,
      "fees": "8,000",
      "rounds": {
        "Round 1": {
          "Intake": 7,
          "AIR": 288479,
          "SML": 21478,
          "CSML": "ST-217"
        },
        "Round 2": {
          "Intake": 0,
          "AIR": 281431,
          "SML": 21064,
          "CSML": "ST-201"
        },
        "Round 3": {
          "Intake": 0,
          "AIR": 300491,
          "SML": 22141,
          "CSML": "ST-246"
        },
        "Stray Round 1": {
          "Intake": 0,
          "AIR": null,
          "SML": null,
          "CSML": null
        },
        "Stray Round 2": {
          "Intake": null,
          "AIR": null,
          "SML": null,
          "CSML": null
        },
        "Stray Round 3": {
          "Intake": null,
          "AIR": null,
          "SML": null,
          "CSML": null
        }
      }
    },
    {
      "code": "1119",
      "name": "Bhausaheb Hire Medical College, Dhule",
      "establishment": 1988,
      "fees": "13,630",
      "rounds": {
        "Round 1": {
          "Intake": 3,
          "AIR": 290373,
          "SML": 21602,
          "CSML": "ST-222"
        },
        "Round 2": {
          "Intake": 1,
          "AIR": 281587,
          "SML": 21073,
          "CSML": "ST-202"
        },
        "Round 3": {
          "Intake": 0,
          "AIR": null,
          "SML": null,
          "CSML": null
        },
        "Stray Round 1": {
          "Intake": 0,
          "AIR": null,
          "SML": null,
          "CSML": null
        },
        "Stray Round 2": {
          "Intake": null,
          "AIR": null,
          "SML": null,
          "CSML": null
        },
        "Stray Round 3": {
          "Intake": null,
          "AIR": null,
          "SML": null,
          "CSML": null
        }
      }
    },
    {
      "code": "1174",
      "name": "ESIC Medical College, Andheri",
      "establishment": 2025,
      "fees": "1,00,000",
      "rounds": {
        "Round 1": {
          "Intake": null,
          "AIR": null,
          "SML": null,
          "CSML": null
        },
        "Round 2": {
          "Intake": 1,
          "AIR": 282978,
          "SML": 21147,
          "CSML": "ST-203"
        },
        "Round 3": {
          "Intake": 0,
          "AIR": null,
          "SML": null,
          "CSML": null
        },
        "Stray Round 1": {
          "Intake": 0,
          "AIR": null,
          "SML": null,
          "CSML": null
        },
        "Stray Round 2": {
          "Intake": null,
          "AIR": null,
          "SML": null,
          "CSML": null
        },
        "Stray Round 3": {
          "Intake": null,
          "AIR": null,
          "SML": null,
          "CSML": null
        }
      }
    },
    {
      "code": "1149",
      "name": "Government Medical College, Jalgaon",
      "establishment": 2018,
      "fees": "12,100",
      "rounds": {
        "Round 1": {
          "Intake": 5,
          "AIR": 295990,
          "SML": 21966,
          "CSML": "ST-234"
        },
        "Round 2": {
          "Intake": 0,
          "AIR": 283585,
          "SML": 21179,
          "CSML": "ST-204"
        },
        "Round 3": {
          "Intake": 1,
          "AIR": 300131,
          "SML": 22116,
          "CSML": "ST-244"
        },
        "Stray Round 1": {
          "Intake": 0,
          "AIR": null,
          "SML": null,
          "CSML": null
        },
        "Stray Round 2": {
          "Intake": null,
          "AIR": null,
          "SML": null,
          "CSML": null
        },
        "Stray Round 3": {
          "Intake": null,
          "AIR": null,
          "SML": null,
          "CSML": null
        }
      }
    },
    {
      "code": "1333",
      "name": "Government Medical College, Latur",
      "establishment": 2002,
      "fees": "11,530",
      "rounds": {
        "Round 1": {
          "Intake": 5,
          "AIR": 287165,
          "SML": 21411,
          "CSML": "ST-215"
        },
        "Round 2": {
          "Intake": 0,
          "AIR": 289537,
          "SML": 21548,
          "CSML": "ST-219"
        },
        "Round 3": {
          "Intake": 0,
          "AIR": 297858,
          "SML": 21965,
          "CSML": "ST-236"
        },
        "Stray Round 1": {
          "Intake": 0,
          "AIR": null,
          "SML": null,
          "CSML": null
        },
        "Stray Round 2": {
          "Intake": null,
          "AIR": null,
          "SML": null,
          "CSML": null
        },
        "Stray Round 3": {
          "Intake": null,
          "AIR": null,
          "SML": null,
          "CSML": null
        }
      }
    },
    {
      "code": "1155",
      "name": "Government Medical College, Satara",
      "establishment": 2021,
      "fees": "10,000",
      "rounds": {
        "Round 1": {
          "Intake": 3,
          "AIR": 301838,
          "SML": 22361,
          "CSML": "ST-256"
        },
        "Round 2": {
          "Intake": 0,
          "AIR": 292999,
          "SML": 21781,
          "CSML": "ST-228"
        },
        "Round 3": {
          "Intake": 1,
          "AIR": 316075,
          "SML": 23095,
          "CSML": "ST-283"
        },
        "Stray Round 1": {
          "Intake": 1,
          "AIR": 371851,
          "SML": 26510,
          "CSML": "ST-469"
        },
        "Stray Round 2": {
          "Intake": null,
          "AIR": 374587,
          "SML": 26655,
          "CSML": "ST-477"
        },
        "Stray Round 3": {
          "Intake": null,
          "AIR": null,
          "SML": null,
          "CSML": null
        }
      }
    },
    {
      "code": "1226",
      "name": "Vasantrao Naik Medical College, Yavatmal",
      "establishment": 1989,
      "fees": "14,100",
      "rounds": {
        "Round 1": {
          "Intake": 7,
          "AIR": 299118,
          "SML": 22158,
          "CSML": "ST-246"
        },
        "Round 2": {
          "Intake": 0,
          "AIR": 296404,
          "SML": 21982,
          "CSML": "ST-235"
        },
        "Round 3": {
          "Intake": 0,
          "AIR": 316651,
          "SML": 23134,
          "CSML": "ST-286"
        },
        "Stray Round 1": {
          "Intake": 0,
          "AIR": null,
          "SML": null,
          "CSML": null
        },
        "Stray Round 2": {
          "Intake": null,
          "AIR": null,
          "SML": null,
          "CSML": null
        },
        "Stray Round 3": {
          "Intake": null,
          "AIR": null,
          "SML": null,
          "CSML": null
        }
      }
    },
    {
      "code": "1164",
      "name": "Government Medical College, Nashik",
      "establishment": 2024,
      "fees": "17,600",
      "rounds": {
        "Round 1": {
          "Intake": 2,
          "AIR": 277133,
          "SML": 20816,
          "CSML": "ST-192"
        },
        "Round 2": {
          "Intake": 0,
          "AIR": 297071,
          "SML": 22016,
          "CSML": "ST-236"
        },
        "Round 3": {
          "Intake": 0,
          "AIR": null,
          "SML": null,
          "CSML": null
        },
        "Stray Round 1": {
          "Intake": 0,
          "AIR": null,
          "SML": null,
          "CSML": null
        },
        "Stray Round 2": {
          "Intake": null,
          "AIR": null,
          "SML": null,
          "CSML": null
        },
        "Stray Round 3": {
          "Intake": null,
          "AIR": null,
          "SML": null,
          "CSML": null
        }
      }
    },
    {
      "code": "1241",
      "name": "Government Medical College, Chandrapur",
      "establishment": 2015,
      "fees": "15,840",
      "rounds": {
        "Round 1": {
          "Intake": 4,
          "AIR": 297784,
          "SML": 22075,
          "CSML": "ST-240"
        },
        "Round 2": {
          "Intake": 1,
          "AIR": 300491,
          "SML": 22258,
          "CSML": "ST-252"
        },
        "Round 3": {
          "Intake": 0,
          "AIR": 308925,
          "SML": 22665,
          "CSML": "ST-269"
        },
        "Stray Round 1": {
          "Intake": 0,
          "AIR": null,
          "SML": null,
          "CSML": null
        },
        "Stray Round 2": {
          "Intake": null,
          "AIR": null,
          "SML": null,
          "CSML": null
        },
        "Stray Round 3": {
          "Intake": null,
          "AIR": null,
          "SML": null,
          "CSML": null
        }
      }
    },
    {
      "code": "1151",
      "name": "Government Medical College, Nandurbar",
      "establishment": 2020,
      "fees": "12,600",
      "rounds": {
        "Round 1": {
          "Intake": 5,
          "AIR": 319592,
          "SML": 23408,
          "CSML": "ST-296"
        },
        "Round 2": {
          "Intake": 0,
          "AIR": 308190,
          "SML": 22737,
          "CSML": "ST-274"
        },
        "Round 3": {
          "Intake": 0,
          "AIR": 311780,
          "SML": 22847,
          "CSML": "ST-275"
        },
        "Stray Round 1": {
          "Intake": 0,
          "AIR": null,
          "SML": null,
          "CSML": null
        },
        "Stray Round 2": {
          "Intake": null,
          "AIR": null,
          "SML": null,
          "CSML": null
        },
        "Stray Round 3": {
          "Intake": null,
          "AIR": null,
          "SML": null,
          "CSML": null
        }
      }
    },
    {
      "code": "1267",
      "name": "Government Medical College, Amravati",
      "establishment": 2024,
      "fees": null,
      "rounds": {
        "Round 1": {
          "Intake": null,
          "AIR": 308190,
          "SML": 22737,
          "CSML": "ST-274"
        },
        "Round 2": {
          "Intake": 0,
          "AIR": 308925,
          "SML": 22788,
          "CSML": "ST-275"
        },
        "Round 3": {
          "Intake": 1,
          "AIR": 324668,
          "SML": 23608,
          "CSML": "ST-300"
        },
        "Stray Round 1": {
          "Intake": 0,
          "AIR": null,
          "SML": null,
          "CSML": null
        },
        "Stray Round 2": {
          "Intake": null,
          "AIR": null,
          "SML": null,
          "CSML": null
        },
        "Stray Round 3": {
          "Intake": null,
          "AIR": null,
          "SML": null,
          "CSML": null
        }
      }
    },
    {
      "code": "1358",
      "name": "Government Medical College, Osmanabad",
      "establishment": 2022,
      "fees": "14,550",
      "rounds": {
        "Round 1": {
          "Intake": 4,
          "AIR": 317303,
          "SML": 23291,
          "CSML": "ST-294"
        },
        "Round 2": {
          "Intake": 0,
          "AIR": 314296,
          "SML": 23127,
          "CSML": "ST-284"
        },
        "Round 3": {
          "Intake": 0,
          "AIR": 325665,
          "SML": 23672,
          "CSML": "ST-302"
        },
        "Stray Round 1": {
          "Intake": 0,
          "AIR": null,
          "SML": null,
          "CSML": null
        },
        "Stray Round 2": {
          "Intake": null,
          "AIR": null,
          "SML": null,
          "CSML": null
        },
        "Stray Round 3": {
          "Intake": null,
          "AIR": null,
          "SML": null,
          "CSML": null
        }
      }
    },
    {
      "code": "1242",
      "name": "Government Medical College, Gondia",
      "establishment": 2016,
      "fees": "17,150",
      "rounds": {
        "Round 1": {
          "Intake": 5,
          "AIR": 316651,
          "SML": 23260,
          "CSML": "ST-292"
        },
        "Round 2": {
          "Intake": 0,
          "AIR": 316075,
          "SML": 23222,
          "CSML": "ST-289"
        },
        "Round 3": {
          "Intake": 0,
          "AIR": 336087,
          "SML": 24320,
          "CSML": "ST-341"
        },
        "Stray Round 1": {
          "Intake": 0,
          "AIR": null,
          "SML": null,
          "CSML": null
        },
        "Stray Round 2": {
          "Intake": null,
          "AIR": null,
          "SML": null,
          "CSML": null
        },
        "Stray Round 3": {
          "Intake": null,
          "AIR": null,
          "SML": null,
          "CSML": null
        }
      }
    },
    {
      "code": "1159",
      "name": "Government Medical College, Ratnagiri",
      "establishment": 2023,
      "fees": "14,000",
      "rounds": {
        "Round 1": {
          "Intake": 2,
          "AIR": 315021,
          "SML": 23158,
          "CSML": "ST-287"
        },
        "Round 2": {
          "Intake": 0,
          "AIR": 317260,
          "SML": 23284,
          "CSML": "ST-293"
        },
        "Round 3": {
          "Intake": 0,
          "AIR": null,
          "SML": null,
          "CSML": null
        },
        "Stray Round 1": {
          "Intake": 0,
          "AIR": null,
          "SML": null,
          "CSML": null
        },
        "Stray Round 2": {
          "Intake": null,
          "AIR": null,
          "SML": null,
          "CSML": null
        },
        "Stray Round 3": {
          "Intake": null,
          "AIR": null,
          "SML": null,
          "CSML": null
        }
      }
    },
    {
      "code": "1166",
      "name": "Government Medical College, Ambernath",
      "establishment": 2024,
      "fees": null,
      "rounds": {
        "Round 1": {
          "Intake": null,
          "AIR": 299098,
          "SML": 22155,
          "CSML": "ST-245"
        },
        "Round 2": {
          "Intake": 0,
          "AIR": 319874,
          "SML": 23434,
          "CSML": "ST-298"
        },
        "Round 3": {
          "Intake": 0,
          "AIR": 329032,
          "SML": 23887,
          "CSML": "ST-313"
        },
        "Stray Round 1": {
          "Intake": 0,
          "AIR": null,
          "SML": null,
          "CSML": null
        },
        "Stray Round 2": {
          "Intake": null,
          "AIR": null,
          "SML": null,
          "CSML": null
        },
        "Stray Round 3": {
          "Intake": null,
          "AIR": null,
          "SML": null,
          "CSML": null
        }
      }
    },
    {
      "code": "1360",
      "name": "Government Medical College, Parbhani",
      "establishment": 2023,
      "fees": "17,800",
      "rounds": {
        "Round 1": {
          "Intake": 3,
          "AIR": 319874,
          "SML": 23434,
          "CSML": "ST-298"
        },
        "Round 2": {
          "Intake": 0,
          "AIR": 322072,
          "SML": 23567,
          "CSML": "ST-302"
        },
        "Round 3": {
          "Intake": 0,
          "AIR": null,
          "SML": null,
          "CSML": null
        },
        "Stray Round 1": {
          "Intake": 0,
          "AIR": null,
          "SML": null,
          "CSML": null
        },
        "Stray Round 2": {
          "Intake": null,
          "AIR": null,
          "SML": null,
          "CSML": null
        },
        "Stray Round 3": {
          "Intake": null,
          "AIR": null,
          "SML": null,
          "CSML": null
        }
      }
    },
    {
      "code": "1248",
      "name": "Mahatma Gandhi Institute of Medical Sciences, Sevagram, Wardha",
      "establishment": 1969,
      "fees": "1,25,700",
      "rounds": {
        "Round 1": {
          "Intake": 4,
          "AIR": 284679,
          "SML": 21251,
          "CSML": "ST-208"
        },
        "Round 2": {
          "Intake": 3,
          "AIR": 325665,
          "SML": 23790,
          "CSML": "ST-309"
        },
        "Round 3": {
          "Intake": 1,
          "AIR": 331335,
          "SML": 24036,
          "CSML": "ST-325"
        },
        "Stray Round 1": {
          "Intake": 1,
          "AIR": 372633,
          "SML": 26551,
          "CSML": "ST-470"
        },
        "Stray Round 2": {
          "Intake": null,
          "AIR": null,
          "SML": null,
          "CSML": null
        },
        "Stray Round 3": {
          "Intake": null,
          "AIR": null,
          "SML": null,
          "CSML": null
        }
      }
    },
    {
      "code": "1371",
      "name": "Government Medical College, Hingoli",
      "establishment": 2024,
      "fees": null,
      "rounds": {
        "Round 1": {
          "Intake": null,
          "AIR": 331998,
          "SML": 24200,
          "CSML": "ST-337"
        },
        "Round 2": {
          "Intake": 1,
          "AIR": 326574,
          "SML": 23839,
          "CSML": "ST-312"
        },
        "Round 3": {
          "Intake": 0,
          "AIR": 338511,
          "SML": 24451,
          "CSML": "ST-353"
        },
        "Stray Round 1": {
          "Intake": 0,
          "AIR": null,
          "SML": null,
          "CSML": null
        },
        "Stray Round 2": {
          "Intake": null,
          "AIR": null,
          "SML": null,
          "CSML": null
        },
        "Stray Round 3": {
          "Intake": null,
          "AIR": null,
          "SML": null,
          "CSML": null
        }
      }
    },
    {
      "code": "1269",
      "name": "Government Medical College, Buldhana",
      "establishment": 2024,
      "fees": null,
      "rounds": {
        "Round 1": {
          "Intake": null,
          "AIR": 329032,
          "SML": 24006,
          "CSML": "ST-320"
        },
        "Round 2": {
          "Intake": 0,
          "AIR": 329914,
          "SML": 24057,
          "CSML": "ST-324"
        },
        "Round 3": {
          "Intake": 0,
          "AIR": 335966,
          "SML": 24316,
          "CSML": "ST-339"
        },
        "Stray Round 1": {
          "Intake": 0,
          "AIR": null,
          "SML": null,
          "CSML": null
        },
        "Stray Round 2": {
          "Intake": null,
          "AIR": null,
          "SML": null,
          "CSML": null
        },
        "Stray Round 3": {
          "Intake": null,
          "AIR": null,
          "SML": null,
          "CSML": null
        }
      }
    },
    {
      "code": "1270",
      "name": "Government Medical College, Washim",
      "establishment": 2024,
      "fees": null,
      "rounds": {
        "Round 1": {
          "Intake": null,
          "AIR": 330184,
          "SML": 24072,
          "CSML": "ST-327"
        },
        "Round 2": {
          "Intake": 0,
          "AIR": 331275,
          "SML": 24143,
          "CSML": "ST-330"
        },
        "Round 3": {
          "Intake": 0,
          "AIR": 331024,
          "SML": 24015,
          "CSML": "ST-322"
        },
        "Stray Round 1": {
          "Intake": 1,
          "AIR": 372649,
          "SML": 26553,
          "CSML": "ST-471"
        },
        "Stray Round 2": {
          "Intake": null,
          "AIR": null,
          "SML": null,
          "CSML": null
        },
        "Stray Round 3": {
          "Intake": null,
          "AIR": null,
          "SML": null,
          "CSML": null
        }
      }
    },
    {
      "code": "1154",
      "name": "Government Medical College, Sindhudurg",
      "establishment": 2021,
      "fees": "10,000",
      "rounds": {
        "Round 1": {
          "Intake": 4,
          "AIR": 322215,
          "SML": 23577,
          "CSML": "ST-303"
        },
        "Round 2": {
          "Intake": 0,
          "AIR": 331289,
          "SML": 24148,
          "CSML": "ST-331"
        },
        "Round 3": {
          "Intake": 1,
          "AIR": 338764,
          "SML": 24478,
          "CSML": "ST-357"
        },
        "Stray Round 1": {
          "Intake": 2,
          "AIR": 371498,
          "SML": 26493,
          "CSML": "ST-468"
        },
        "Stray Round 2": {
          "Intake": null,
          "AIR": null,
          "SML": null,
          "CSML": null
        },
        "Stray Round 3": {
          "Intake": null,
          "AIR": null,
          "SML": null,
          "CSML": null
        }
      }
    },
    {
      "code": "1268",
      "name": "Government Medical College, Bhandara",
      "establishment": 2024,
      "fees": null,
      "rounds": {
        "Round 1": {
          "Intake": null,
          "AIR": 331541,
          "SML": 24172,
          "CSML": "ST-334"
        },
        "Round 2": {
          "Intake": 0,
          "AIR": 336072,
          "SML": 24434,
          "CSML": "ST-347"
        },
        "Round 3": {
          "Intake": 0,
          "AIR": 343520,
          "SML": 24750,
          "CSML": "ST-374"
        },
        "Stray Round 1": {
          "Intake": 1,
          "AIR": 373537,
          "SML": 26606,
          "CSML": "ST-474"
        },
        "Stray Round 2": {
          "Intake": null,
          "AIR": null,
          "SML": null,
          "CSML": null
        },
        "Stray Round 3": {
          "Intake": null,
          "AIR": null,
          "SML": null,
          "CSML": null
        }
      }
    },
    {
      "code": "1373",
      "name": "Government Medical College, Gadchiroli",
      "establishment": 2024,
      "fees": null,
      "rounds": {
        "Round 1": {
          "Intake": null,
          "AIR": 333988,
          "SML": 24313,
          "CSML": "ST-342"
        },
        "Round 2": {
          "Intake": 1,
          "AIR": 337268,
          "SML": 24507,
          "CSML": "ST-352"
        },
        "Round 3": {
          "Intake": 0,
          "AIR": 343334,
          "SML": 24735,
          "CSML": "ST-373"
        },
        "Stray Round 1": {
          "Intake": 0,
          "AIR": null,
          "SML": null,
          "CSML": null
        },
        "Stray Round 2": {
          "Intake": null,
          "AIR": null,
          "SML": null,
          "CSML": null
        },
        "Stray Round 3": {
          "Intake": null,
          "AIR": null,
          "SML": null,
          "CSML": null
        }
      }
    },
    {
      "code": "1372",
      "name": "Government Medical College, Jalna",
      "establishment": 2024,
      "fees": null,
      "rounds": {
        "Round 1": {
          "Intake": null,
          "AIR": 326509,
          "SML": 23832,
          "CSML": "ST-311"
        },
        "Round 2": {
          "Intake": 0,
          "AIR": null,
          "SML": null,
          "CSML": null
        },
        "Round 3": {
          "Intake": 0,
          "AIR": 326574,
          "SML": 23721,
          "CSML": "ST-305"
        },
        "Stray Round 1": {
          "Intake": 0,
          "AIR": null,
          "SML": null,
          "CSML": null
        },
        "Stray Round 2": {
          "Intake": null,
          "AIR": null,
          "SML": null,
          "CSML": null
        },
        "Stray Round 3": {
          "Intake": null,
          "AIR": null,
          "SML": null,
          "CSML": null
        }
      }
    },
    {
      "code": "1153",
      "name": "Government Medical College, Alibaug",
      "establishment": 2021,
      "fees": "13,610",
      "rounds": {
        "Round 1": {
          "Intake": 4,
          "AIR": 306212,
          "SML": 22631,
          "CSML": "ST-267"
        },
        "Round 2": {
          "Intake": 0,
          "AIR": null,
          "SML": null,
          "CSML": null
        },
        "Round 3": {
          "Intake": 0,
          "AIR": 328927,
          "SML": 23876,
          "CSML": "ST-310"
        },
        "Stray Round 1": {
          "Intake": 0,
          "AIR": null,
          "SML": null,
          "CSML": null
        },
        "Stray Round 2": {
          "Intake": null,
          "AIR": null,
          "SML": null,
          "CSML": null
        },
        "Stray Round 3": {
          "Intake": null,
          "AIR": null,
          "SML": null,
          "CSML": null
        }
      }
    },
    {
      "code": "1140",
      "name": "HBT & Cooper Government Medical College, Mumbai",
      "establishment": 2015,
      "fees": "8,900",
      "rounds": {
        "Round 1": {
          "Intake": 8,
          "AIR": 222258,
          "SML": 17393,
          "CSML": "ST-102"
        },
        "Round 2": {
          "Intake": 0,
          "AIR": null,
          "SML": null,
          "CSML": null
        },
        "Round 3": {
          "Intake": 0,
          "AIR": null,
          "SML": null,
          "CSML": null
        },
        "Stray Round 1": {
          "Intake": 0,
          "AIR": null,
          "SML": null,
          "CSML": null
        },
        "Stray Round 2": {
          "Intake": null,
          "AIR": null,
          "SML": null,
          "CSML": null
        },
        "Stray Round 3": {
          "Intake": null,
          "AIR": null,
          "SML": null,
          "CSML": null
        }
      }
    }
  ]
}